setup.py
amueller/__init__.py
amueller.egg-info/PKG-INFO
amueller.egg-info/SOURCES.txt
amueller.egg-info/dependency_links.txt
amueller.egg-info/top_level.txt