Metadata-Version: 1.0
Name: amueller
Version: 1.0
Summary: It's me
Home-page: https://amueller.github.io
Author: Andreas Mueller
Author-email: t3kcit+vanity@gmail.com
License: MIT
Platform: UNKNOWN
